README.txt
setup.cfg
setup.py
django_garcimore.egg-info/PKG-INFO
django_garcimore.egg-info/SOURCES.txt
django_garcimore.egg-info/dependency_links.txt
django_garcimore.egg-info/entry_points.txt
django_garcimore.egg-info/not-zip-safe
django_garcimore.egg-info/top_level.txt
garcimore/__init__.py
garcimore/utils.py