Metadata-Version: 1.0
Name: django-garcimore
Version: 1.0
Summary: A magic trick to make Django disappear
Home-page: http://github.com/gawel/django-garcimore
Author: Gael Pasgrimaud
Author-email: gael@gawel.org
License: MIT
Keywords: django garcimore magic
Platform: UNKNOWN
Classifier: Framework :: Django
Classifier: Intended Audience :: Developers
Classifier: License :: OSI Approved :: MIT License
Classifier: Operating System :: OS Independent
Classifier: Development Status :: 5 - Production/Stable
